kerberoast/__init__.py
kerberoast/_version.py
kerberoast/kerberoast.py
kerberoast-0.2.0.dist-info/LICENSE
kerberoast-0.2.0.dist-info/METADATA
kerberoast-0.2.0.dist-info/WHEEL
kerberoast-0.2.0.dist-info/entry_points.txt
kerberoast-0.2.0.dist-info/top_level.txt
kerberoast-0.2.0.dist-info/zip-safe
kerberoast-0.2.0.dist-info/RECORD
